Workbook
Name Slicer_Inventory_Value: #N/A
Name Slicer_Product_ID: #N/A
Name Slicer_Supplier_ID: #N/A

Sheet Dashboard
A1: SUPPLY CHAIN ANALYTICS DASHBOARD
A3: Interactive Dashboard | Sales | Inventory | Procurement
A7: Purchase Cost by Supplier | E7: Total Sales Revenue | I7: Inventory Value | M7: Total Products
A10: =SUM(Purchase_Orders!G2:G11) -> 2359000 | E10: =SUM(Sales_Orders!G2:G11) -> 927900 | I10: =SUM(Inventory!G2:G10) -> 3647000 | M10: =COUNTA(Products!A2:A11) -> 10
A13: Total Suppliers
E14: Top Customers by Sales | I14: Total Shipping Cost | M14: Average Transit Days
A17: =COUNTA(Suppliers!A2:A6) -> 5 | E17: =COUNTA('Customers'!A2:A11) -> 10 | I17: =SUM(Shipments!H2:H11) -> 4990 | M17: =AVERAGE(Shipments!J2:J11) -> 3.2

Sheet Pivot_Tables
A3: Product ID | B3: Total Sales Revenue (₹) | E3: Supplier ID | F3: Total Purchase Cost (₹) | I3: Row Labels | J3: Inventory Status | M3: Customer ID | N3: Sales Revenue (₹)
A4: P001 | B4: 275000 | E4: S001 | F4: 1530000 | I4: In Stock | J4: 8 | M4: C001 | N4: 275000
A5: P002 | B5: 250000 | E5: S003 | F5: 351000 | I5: Reorder | J5: 1 | M5: C002 | N5: 250000
A6: P005 | B6: 78000 | E6: S004 | F6: 226000 | I6: Grand Total | J6: 9 | M6: C005 | N6: 78000
A7: P006 | B7: 76000 | E7: S005 | F7: 139500 | M7: C006 | N7: 76000
A8: P008 | B8: 58500 | E8: S002 | F8: 112500 | M8: C008 | N8: 58500
A9: P007 | B9: 50400 | E9: Grand Total | F9: 2359000 | M9: C007 | N9: 50400
A10: P009 | B10: 44000 | M10: C009 | N10: 44000
A11: P010 | B11: 42000 | M11: C010 | N11: 42000
A12: P003 | B12: 30000 | M12: C003 | N12: 30000
A13: P004 | B13: 24000 | M13: C004 | N13: 24000
A14: Grand Total | B14: 927900 | M14: Grand Total | N14: 927900
A17: Delivery_Status | B17: Count of Shipment_ID | E17: Carrier | F17: Sum of Transit Days | I17: Product_ID | J17: Quantity (Sum) | M17: Carrier | N17: Shipment_ID (Count)
A18: Delayed | B18: 1 | E18: FedEx | F18: 12 | I18: P004 | J18: 30 | M18: FedEx | N18: 3
A19: Delivered | B19: 7 | E19: DHL | F19: 9 | I19: P003 | J19: 25 | M19: DHL | N19: 3
A20: In Transit | B20: 2 | E20: Delhivery | F20: 7 | I20: P009 | J20: 20 | M20: Blue Dart | N20: 2
A21: Grand Total | B21: 10 | E21: Blue Dart | F21: 4 | I21: P010 | J21: 15 | M21: Delhivery | N21: 2
E22: Grand Total | F22: 32 | I22: P007 | J22: 12 | M22: Grand Total | N22: 10
I23: P002 | J23: 10
A24: Product_ID | B24: Sum of Inventory_Value | I24: P008 | J24: 9
A25: P002 | B25: 1710000 | I25: P006 | J25: 8
A26: P005 | B26: 603000 | I26: P005 | J26: 6
A27: P006 | B27: 301000 | I27: P001 | J27: 5
A28: P008 | B28: 273000 | I28: Grand Total | J28: 140
A29: P007 | B29: 187500
A30: P003 | B30: 168000
A31: P010 | B31: 157500
A32: P009 | B32: 156000
A33: P004 | B33: 91000
A34: Grand Total | B34: 3647000

Sheet Products
A1: Product_ID | B1: Product_Name | C1: Category | D1: Unit_Cost | E1: Selling_Price | F1: Lead_Time | G1: Safety_Stock | H1: Reorder_Point | I1: Supplier_ID
A2: P001 | B2: Laptop | C2: Electronics | D2: 45000 | E2: 55000 | F2: 10 | G2: 20 | H2: 50 | I2: S001
A3: P002 | B3: Smartphone | C3: Electronics | D3: 18000 | E3: 25000 | F3: 7 | G3: 30 | H3: 70 | I3: S001
A4: P003 | B4: Keyboard | C4: Accessories | D4: 600 | E4: 1200 | F4: 5 | G4: 50 | H4: 100 | I4: S002
A5: P004 | B5: Mouse | C5: Accessories | D5: 350 | E5: 800 | F5: 4 | G5: 60 | H5: 120 | I5: S002
A6: P005 | B6: Monitor | C6: Electronics | D6: 9000 | E6: 13000 | F6: 8 | G6: 25 | H6: 60 | I6: S003
A7: P006 | B7: Printer | C7: Office | D7: 7000 | E7: 9500 | F7: 12 | G7: 15 | H7: 40 | I7: S003
A8: P007 | B8: Router | C8: Networking | D8: 2500 | E8: 4200 | F8: 6 | G8: 35 | H8: 80 | I8: S004
A9: P008 | B9: SSD 1TB | C9: Storage | D9: 4200 | E9: 6500 | F9: 9 | G9: 25 | H9: 55 | I9: S004
A10: P009 | B10: Webcam | C10: Accessories | D10: 1200 | E10: 2200 | F10: 5 | G10: 40 | H10: 90 | I10: S005
A11: P010 | B11: Headphones | C11: Accessories | D11: 1500 | E11: 2800 | F11: 6 | G11: 45 | H11: 95 | I11: S005

Sheet Suppliers
A1: Supplier_ID | B1: Supplier_Name | C1: City | D1: Country | E1: Lead_Time_Days | F1: Rating
A2: S001 | B2: TechSource Ltd | C2: Bengaluru | D2: India | E2: 10 | F2: 4.8
A3: S002 | B3: Accessory Hub | C3: Delhi | D3: India | E3: 5 | F3: 4.5
A4: S003 | B4: OfficeTech Pvt Ltd | C4: Mumbai | D4: India | E4: 12 | F4: 4.6
A5: S004 | B5: NetConnect Solutions | C5: Hyderabad | D5: India | E5: 8 | F5: 4.7
A6: S005 | B6: Digital Devices Co | C6: Chennai | D6: India | E6: 6 | F6: 4.4

Sheet Customers
A1: Customer_ID | B1: Customer_Name | C1: City | D1: State | E1: Customer_Type
A2: C001 | B2: Reliance Digital | C2: Mumbai | D2: Maharashtra | E2: Retail
A3: C002 | B3: Croma | C3: Bengaluru | D3: Karnataka | E3: Retail
A4: C003 | B4: Vijay Sales | C4: Delhi | D4: Delhi | E4: Retail
A5: C004 | B5: Amazon India | C5: Hyderabad | D5: Telangana | E5: E-commerce
A6: C005 | B6: Flipkart | C6: Bengaluru | D6: Karnataka | E6: E-commerce
A7: C006 | B7: Tata Cliq | C7: Mumbai | D7: Maharashtra | E7: E-commerce
A8: C007 | B8: Poorvika Mobiles | C8: Chennai | D8: Tamil Nadu | E8: Retail
A9: C008 | B9: Sangeetha Mobiles | C9: Bengaluru | D9: Karnataka | E9: Retail
A10: C009 | B10: Lotus Electronics | C10: Indore | D10: Madhya Pradesh | E10: Retail
A11: C010 | B11: Pai International | C11: Bengaluru | D11: Karnataka | E11: Retail

Sheet Purchase_Orders
A1: Purchase_Order_ID | B1: Order_Date | C1: Product_ID | D1: Supplier_ID | E1: Quantity | F1: Unit_Cost | G1: Total_Cost | H1: Expected_Delivery | I1: Status
A2: PO001 | B2: 46028 | C2: P001 | D2: S001 | E2: 20 | F2: =_xlfn.XLOOKUP(Table6[[#This Row],[Product_ID]],products[Product_ID],products[Unit_Cost]) -> 45000 | G2: =Table6[[#This Row],[Quantity]]*Table6[[#This Row],[Unit_Cost]] -> 900000 | H2: =B2+_xlfn.XLOOKUP(D2,Suppliers!A:A,Suppliers!E:E) -> 46038 | I2: Delivered
A3: PO002 | B3: 46059 | C3: P002 | D3: S001 | E3: 35 | F3: =_xlfn.XLOOKUP(Table6[[#This Row],[Product_ID]],products[Product_ID],products[Unit_Cost]) -> 18000 | G3: =Table6[[#This Row],[Quantity]]*Table6[[#This Row],[Unit_Cost]] -> 630000 | H3: =B3+_xlfn.XLOOKUP(D3,Suppliers!A:A,Suppliers!E:E) -> 46069 | I3: Delivered
A4: PO003 | B4: 46087 | C4: P003 | D4: S002 | E4: 100 | F4: =_xlfn.XLOOKUP(Table6[[#This Row],[Product_ID]],products[Product_ID],products[Unit_Cost]) -> 600 | G4: =Table6[[#This Row],[Quantity]]*Table6[[#This Row],[Unit_Cost]] -> 60000 | H4: =B4+_xlfn.XLOOKUP(D4,Suppliers!A:A,Suppliers!E:E) -> 46092 | I4: Delivered
A5: PO004 | B5: 46118 | C5: P004 | D5: S002 | E5: 150 | F5: =_xlfn.XLOOKUP(Table6[[#This Row],[Product_ID]],products[Product_ID],products[Unit_Cost]) -> 350 | G5: =Table6[[#This Row],[Quantity]]*Table6[[#This Row],[Unit_Cost]] -> 52500 | H5: =B5+_xlfn.XLOOKUP(D5,Suppliers!A:A,Suppliers!E:E) -> 46123 | I5: Pending
A6: PO005 | B6: 46148 | C6: P005 | D6: S003 | E6: 25 | F6: =_xlfn.XLOOKUP(Table6[[#This Row],[Product_ID]],products[Product_ID],products[Unit_Cost]) -> 9000 | G6: =Table6[[#This Row],[Quantity]]*Table6[[#This Row],[Unit_Cost]] -> 225000 | H6: =B6+_xlfn.XLOOKUP(D6,Suppliers!A:A,Suppliers!E:E) -> 46160 | I6: Delivered
A7: PO006 | B7: 46179 | C7: P006 | D7: S003 | E7: 18 | F7: =_xlfn.XLOOKUP(Table6[[#This Row],[Product_ID]],products[Product_ID],products[Unit_Cost]) -> 7000 | G7: =Table6[[#This Row],[Quantity]]*Table6[[#This Row],[Unit_Cost]] -> 126000 | H7: =B7+_xlfn.XLOOKUP(D7,Suppliers!A:A,Suppliers!E:E) -> 46191 | I7: Pending
A8: PO007 | B8: 46209 | C8: P007 | D8: S004 | E8: 40 | F8: =_xlfn.XLOOKUP(Table6[[#This Row],[Product_ID]],products[Product_ID],products[Unit_Cost]) -> 2500 | G8: =Table6[[#This Row],[Quantity]]*Table6[[#This Row],[Unit_Cost]] -> 100000 | H8: =B8+_xlfn.XLOOKUP(D8,Suppliers!A:A,Suppliers!E:E) -> 46217 | I8: Delivered
A9: PO008 | B9: 46240 | C9: P008 | D9: S004 | E9: 30 | F9: =_xlfn.XLOOKUP(Table6[[#This Row],[Product_ID]],products[Product_ID],products[Unit_Cost]) -> 4200 | G9: =Table6[[#This Row],[Quantity]]*Table6[[#This Row],[Unit_Cost]] -> 126000 | H9: =B9+_xlfn.XLOOKUP(D9,Suppliers!A:A,Suppliers!E:E) -> 46248 | I9: In Transit
A10: PO009 | B10: 46271 | C10: P009 | D10: S005 | E10: 60 | F10: =_xlfn.XLOOKUP(Table6[[#This Row],[Product_ID]],products[Product_ID],products[Unit_Cost]) -> 1200 | G10: =Table6[[#This Row],[Quantity]]*Table6[[#This Row],[Unit_Cost]] -> 72000 | H10: =B10+_xlfn.XLOOKUP(D10,Suppliers!A:A,Suppliers!E:E) -> 46277 | I10: Delivered
A11: PO010 | B11: 46301 | C11: P010 | D11: S005 | E11: 45 | F11: =_xlfn.XLOOKUP(Table6[[#This Row],[Product_ID]],products[Product_ID],products[Unit_Cost]) -> 1500 | G11: =Table6[[#This Row],[Quantity]]*Table6[[#This Row],[Unit_Cost]] -> 67500 | H11: =B11+_xlfn.XLOOKUP(D11,Suppliers!A:A,Suppliers!E:E) -> 46307 | I11: In Transit

Sheet Inventory
A1: Inventory_ID | B1: Product_ID | C1: Opening_Stock | D1: Stock_In | E1: Stock_Out | F1: Current_Stock | G1: Inventory_Value | H1: Stock_Status
A2: INV002 | B2: P002 | C2: 80 | D2: 35 | E2: 20 | F2: =C2+D2-E2 -> 95 | G2: =F2*_xlfn.XLOOKUP(B2,products[Product_ID],products[Unit_Cost]) -> 1710000 | H2: =IF(F2<=_xlfn.XLOOKUP(B2,products[Product_ID],products[Reorder_Point],0),"Reorder","In Stock") -> In Stock
A3: INV003 | B3: P003 | C3: 300 | D3: 100 | E3: 120 | F3: =C3+D3-E3 -> 280 | G3: =F3*_xlfn.XLOOKUP(B3,products[Product_ID],products[Unit_Cost]) -> 168000 | H3: =IF(F3<=_xlfn.XLOOKUP(B3,products[Product_ID],products[Reorder_Point],0),"Reorder","In Stock") -> In Stock
A4: INV004 | B4: P004 | C4: 250 | D4: 150 | E4: 140 | F4: =C4+D4-E4 -> 260 | G4: =F4*_xlfn.XLOOKUP(B4,products[Product_ID],products[Unit_Cost]) -> 91000 | H4: =IF(F4<=_xlfn.XLOOKUP(B4,products[Product_ID],products[Reorder_Point],0),"Reorder","In Stock") -> In Stock
A5: INV005 | B5: P005 | C5: 60 | D5: 25 | E5: 18 | F5: =C5+D5-E5 -> 67 | G5: =F5*_xlfn.XLOOKUP(B5,products[Product_ID],products[Unit_Cost]) -> 603000 | H5: =IF(F5<=_xlfn.XLOOKUP(B5,products[Product_ID],products[Reorder_Point],0),"Reorder","In Stock") -> In Stock
A6: INV006 | B6: P006 | C6: 40 | D6: 18 | E6: 15 | F6: =C6+D6-E6 -> 43 | G6: =F6*_xlfn.XLOOKUP(B6,products[Product_ID],products[Unit_Cost]) -> 301000 | H6: =IF(F6<=_xlfn.XLOOKUP(B6,products[Product_ID],products[Reorder_Point],0),"Reorder","In Stock") -> In Stock
A7: INV007 | B7: P007 | C7: 90 | D7: 40 | E7: 55 | F7: =C7+D7-E7 -> 75 | G7: =F7*_xlfn.XLOOKUP(B7,products[Product_ID],products[Unit_Cost]) -> 187500 | H7: =IF(F7<=_xlfn.XLOOKUP(B7,products[Product_ID],products[Reorder_Point],0),"Reorder","In Stock") -> Reorder
A8: INV008 | B8: P008 | C8: 75 | D8: 30 | E8: 40 | F8: =C8+D8-E8 -> 65 | G8: =F8*_xlfn.XLOOKUP(B8,products[Product_ID],products[Unit_Cost]) -> 273000 | H8: =IF(F8<=_xlfn.XLOOKUP(B8,products[Product_ID],products[Reorder_Point],0),"Reorder","In Stock") -> In Stock
A9: INV009 | B9: P009 | C9: 150 | D9: 60 | E9: 80 | F9: =C9+D9-E9 -> 130 | G9: =F9*_xlfn.XLOOKUP(B9,products[Product_ID],products[Unit_Cost]) -> 156000 | H9: =IF(F9<=_xlfn.XLOOKUP(B9,products[Product_ID],products[Reorder_Point],0),"Reorder","In Stock") -> In Stock
A10: INV010 | B10: P010 | C10: 110 | D10: 45 | E10: 50 | F10: =C10+D10-E10 -> 105 | G10: =F10*_xlfn.XLOOKUP(B10,products[Product_ID],products[Unit_Cost]) -> 157500 | H10: =IF(F10<=_xlfn.XLOOKUP(B10,products[Product_ID],products[Reorder_Point],0),"Reorder","In Stock") -> In Stock

Sheet Sales_Orders
A1: Sales_Order_ID | B1: Order_Date | C1: Customer_ID | D1: Product_ID | E1: Quantity | F1: Selling_Price | G1: Total_Sales | H1: Order_Status
A2: SO001 | B2: 46059 | C2: C001 | D2: P001 | E2: 5 | F2: =_xlfn.XLOOKUP(D2,products[Product_ID],products[Selling_Price]) -> 55000 | G2: =E2*F2 -> 275000 | H2: Delivered
A3: SO002 | B3: 46087 | C3: C002 | D3: P002 | E3: 10 | F3: =_xlfn.XLOOKUP(D3,products[Product_ID],products[Selling_Price]) -> 25000 | G3: =E3*F3 -> 250000 | H3: Delivered
A4: SO003 | B4: 46118 | C4: C003 | D4: P003 | E4: 25 | F4: =_xlfn.XLOOKUP(D4,products[Product_ID],products[Selling_Price]) -> 1200 | G4: =E4*F4 -> 30000 | H4: Delivered
A5: SO004 | B5: 46148 | C5: C004 | D5: P004 | E5: 30 | F5: =_xlfn.XLOOKUP(D5,products[Product_ID],products[Selling_Price]) -> 800 | G5: =E5*F5 -> 24000 | H5: Pending
A6: SO005 | B6: 46179 | C6: C005 | D6: P005 | E6: 6 | F6: =_xlfn.XLOOKUP(D6,products[Product_ID],products[Selling_Price]) -> 13000 | G6: =E6*F6 -> 78000 | H6: Delivered
A7: SO006 | B7: 46209 | C7: C006 | D7: P006 | E7: 8 | F7: =_xlfn.XLOOKUP(D7,products[Product_ID],products[Selling_Price]) -> 9500 | G7: =E7*F7 -> 76000 | H7: Delivered
A8: SO007 | B8: 46240 | C8: C007 | D8: P007 | E8: 12 | F8: =_xlfn.XLOOKUP(D8,products[Product_ID],products[Selling_Price]) -> 4200 | G8: =E8*F8 -> 50400 | H8: Cancelled
A9: SO008 | B9: 46271 | C9: C008 | D9: P008 | E9: 9 | F9: =_xlfn.XLOOKUP(D9,products[Product_ID],products[Selling_Price]) -> 6500 | G9: =E9*F9 -> 58500 | H9: Delivered
A10: SO009 | B10: 46301 | C10: C009 | D10: P009 | E10: 20 | F10: =_xlfn.XLOOKUP(D10,products[Product_ID],products[Selling_Price]) -> 2200 | G10: =E10*F10 -> 44000 | H10: Delivered
A11: SO010 | B11: 46332 | C11: C010 | D11: P010 | E11: 15 | F11: =_xlfn.XLOOKUP(D11,products[Product_ID],products[Selling_Price]) -> 2800 | G11: =E11*F11 -> 42000 | H11: Pending

Sheet Shipments
A1: Shipment_ID | B1: Sales_Order_ID | C1: Customer_ID | D1: Product_ID | E1: Ship_Date | F1: Delivery_Date | G1: Carrier | H1: Shipping_Cost | I1: Delivery_Status | J1: Transit_Days.
A2: SH001 | B2: SO001 | C2: C001 | D2: P001 | E2: 45659 | F2: 45662 | G2: DHL | H2: 450 | I2: Delivered | J2: =F2-E2 -> 3
A3: SH002 | B3: SO002 | C3: C002 | D3: P002 | E3: 45660 | F3: 45664 | G3: FedEx | H3: 520 | I3: Delivered | J3: =F3-E3 -> 4
A4: SH003 | B4: SO003 | C4: C003 | D4: P003 | E4: 45661 | F4: 45663 | G4: Blue Dart | H4: 390 | I4: Delivered | J4: =F4-E4 -> 2
A5: SH004 | B5: SO004 | C5: C004 | D5: P004 | E5: 45662 | F5: 45666 | G5: Delhivery | H5: 610 | I5: In Transit | J5: =F5-E5 -> 4
A6: SH005 | B6: SO005 | C6: C005 | D6: P005 | E6: 45663 | F6: 45665 | G6: DHL | H6: 430 | I6: Delivered | J6: =F6-E6 -> 2
A7: SH006 | B7: SO006 | C7: C006 | D7: P006 | E7: 45664 | F7: 45668 | G7: FedEx | H7: 580 | I7: Delayed | J7: =F7-E7 -> 4
A8: SH007 | B8: SO007 | C8: C007 | D8: P007 | E8: 45665 | F8: 45667 | G8: Blue Dart | H8: 370 | I8: Delivered | J8: =F8-E8 -> 2
A9: SH008 | B9: SO008 | C9: C008 | D9: P008 | E9: 45666 | F9: 45669 | G9: Delhivery | H9: 550 | I9: Delivered | J9: =F9-E9 -> 3
A10: SH009 | B10: SO009 | C10: C009 | D10: P009 | E10: 45667 | F10: 45671 | G10: DHL | H10: 470 | I10: In Transit | J10: =F10-E10 -> 4
A11: SH010 | B11: SO010 | C11: C010 | D11: P010 | E11: 45668 | F11: 45672 | G11: FedEx | H11: 620 | I11: Delivered | J11: =F11-E11 -> 4

Sheet Insights
A1: Business Area | B1: Insight / Observation
A3: SALES INSIGHTS
A5: Total Sales Revenue | B5: =SUM(Table5[Total_Sales]) -> 927900
A6: Highest Selling Product | B6: =_xlfn.XLOOKUP(Pivot_Tables!I18,products[Product_ID],products[Product_Name]) -> Mouse
A7: Highest Revenue Product | B7: =_xlfn.XLOOKUP(Pivot_Tables!A4,products[Product_ID],products[Product_Name]) -> Laptop
A8: Top Customer by Revenue | B8: =_xlfn.XLOOKUP(Pivot_Tables!M4,Customers[Customer_ID],Customers[Customer_Name]) -> Reliance Digital
A9: Total Sales Orders | B9: =COUNTA(Table5[Sales_Order_ID]) -> 10
A10: Average Order Value | B10: =AVERAGE(Table5[Total_Sales]) -> 92790
A12: PROCUREMENT INSIGHTS
A14: Total Purchase Cost | B14: =SUM(Table6[Total_Cost]) -> 2359000
A15: Highest Purchase Supplier | B15: =_xlfn.XLOOKUP(Pivot_Tables!E4,Suppliers[Supplier_ID],Suppliers[Supplier_Name]) -> TechSource Ltd
A16: Total Purchase Orders | B16: =COUNTA(Table6[Purchase_Order_ID]) -> 10
A17: Average Supplier Lead Time | B17: =AVERAGE(Suppliers[Lead_Time_Days]) -> 8.2
A18: Best Rated Supplier | B18: =_xlfn.XLOOKUP(MAX(Suppliers[Rating]),Suppliers[Rating],Suppliers[Supplier_Name]) -> TechSource Ltd
A20: INVENTORY INSIGHTS
A22: Total Inventory Value | B22: =SUM(Table4[Inventory_Value]) -> 3647000
A23: Products Requiring Reorder | B23: =COUNTIF(Table4[Stock_Status],"Reorder") -> 1
A24: Products In Stock | B24: =COUNTIF(Table4[Stock_Status],"In Stock") -> 8
A25: Highest Inventory Value Product | B25: =_xlfn.XLOOKUP(Pivot_Tables!A25,products[Product_ID],products[Product_Name]) -> Smartphone
A26: Average Current Stock | B26: =AVERAGE(Table4[Current_Stock]) -> 124.44444
A28: LOGISTICS INSIGHTS
A30: Total Shipping Cost | B30: =SUM(Table7[Shipping_Cost]) -> 4990
A31: Average Transit Days | B31: =AVERAGE(Table7[Transit_Days.]) -> 3.2
A32: Delayed Shipments | B32: =Pivot_Tables!B18 -> 1
A33: On-Time Deliveries | B33: =Pivot_Tables!B19 -> 7
A34: Most Used Carrier | B34: =Pivot_Tables!M18 -> FedEx
A36: BUSINESS RECOMMENDATIONS
A38: Sales | B38: Focus marketing efforts on the highest-selling products to maximize revenue.
A39: Procurement | B39: Strengthen relationships with high-performing suppliers and monitor supplier lead times.
A40: Inventory | B40: Reorder products below the reorder point to prevent stock shortages.
A41: Logistics | B41: Reduce delivery delays by monitoring carrier performance and improving shipment planning.
A42: Overall | B42: Continue tracking KPIs regularly to improve operational efficiency and support data-driven decision-making.
